cosyvoice/__init__.py
cosyvoice/client.py
cosyvoice/_internal/__init__.py
cosyvoice/_internal/config.py
cosyvoice/_internal/connection.py
cosyvoice/_internal/state.py
cosyvoice/models/__init__.py
cosyvoice/models/enums.py
cosyvoice/models/speaker.py
cosyvoice/models/synthesis.py
cosyvoice/speaker/__init__.py
cosyvoice/speaker/manager.py
cosyvoice/speaker/models.py
cosyvoice/stream/__init__.py
cosyvoice/stream/client.py
cosyvoice/stream/handlers.py
cosyvoice/stream/protocol.py
cosyvoice/stream/session.py
cosyvoice/utils/__init__.py
cosyvoice/utils/audio.py
cosyvoice/utils/exceptions.py
cosyvoice/utils/validation.py
cosyvoice_client-1.0.4.dist-info/METADATA
cosyvoice_client-1.0.4.dist-info/WHEEL
cosyvoice_client-1.0.4.dist-info/RECORD
