Metadata-Version: 2.4
Name: cosyvoice-client
Version: 1.0.4
Summary: Asynchronous streaming TTS client for CosyVoice
Project-URL: Homepage, https://github.com/cosyvoice/cosyvoice-python
Project-URL: Documentation, https://cosyvoice.github.io/cosyvoice-python
Project-URL: Repository, https://github.com/cosyvoice/cosyvoice-python
Project-URL: Bug Tracker, https://github.com/cosyvoice/cosyvoice-python/issues
Author-email: CosyVoice Team <noreply@cosyvoice.com>
License: MIT
Keywords: async,speech-synthesis,streaming,tts,websocket
Classifier: Development Status :: 4 - Beta
Classifier: Intended Audience :: Developers
Classifier: License :: OSI Approved :: MIT License
Classifier: Programming Language :: Python :: 3
Classifier: Programming Language :: Python :: 3.10
Classifier: Programming Language :: Python :: 3.11
Classifier: Programming Language :: Python :: 3.12
Classifier: Topic :: Multimedia :: Sound/Audio :: Speech
Classifier: Topic :: Software Development :: Libraries :: Python Modules
Requires-Python: >=3.10
Requires-Dist: aiofiles>=23.0.0
Requires-Dist: aiohttp>=3.9.0
Requires-Dist: autopep8>=2.3.2
Requires-Dist: numpy>=1.24.0
Requires-Dist: pydantic>=2.5.0
Requires-Dist: websockets>=12.0
Provides-Extra: dev
Requires-Dist: black>=23.0.0; extra == 'dev'
Requires-Dist: isort>=5.12.0; extra == 'dev'
Requires-Dist: mypy>=1.7.0; extra == 'dev'
Requires-Dist: pytest-asyncio>=0.21.0; extra == 'dev'
Requires-Dist: pytest-cov>=4.1.0; extra == 'dev'
Requires-Dist: pytest-mock>=3.11.0; extra == 'dev'
Requires-Dist: pytest>=7.4.0; extra == 'dev'
Requires-Dist: python-dotenv>=1.0.0; extra == 'dev'
Requires-Dist: ruff>=0.1.0; extra == 'dev'
Provides-Extra: docs
Requires-Dist: mkdocs-material>=9.4.0; extra == 'docs'
Requires-Dist: mkdocs>=1.5.0; extra == 'docs'
Requires-Dist: mkdocstrings[python]>=0.24.0; extra == 'docs'
Provides-Extra: examples
Requires-Dist: sounddevice>=0.4.6; extra == 'examples'
